{"_ts":[1556740338],"_r":{"breakdown":{"html":{"bytes":[286187],"requests":[19]},"js":{"bytes":[2489971],"requests":[67]},"css":{"bytes":[293860],"requests":[10]},"image":{"bytes":[2941060],"requests":[135]},"flash":{"bytes":[0],"requests":[0]},"font":{"bytes":[52384],"requests":[3]},"video":{"bytes":[0],"requests":[0]},"other":{"bytes":[2602],"requests":[34]}},"date":[1556740338],"domElements":[2556],"domInteractive":[5156],"firstPaint":[5024.0750000003],"fullyLoaded":[16888],"id":["190501_9F_6a579db6b98f1028a5d889812b610544"],"loadTime":[13744],"render":[5100],"SpeedIndex":[13232],"TTFB":[1594],"TTFI":[6129],"TimeToInteractive":[null],"firstContentfulPaint":[5024],"firstMeaningfulPaint":[7206],"videoFrames":[[{"_i":"ms_000000.jpg","_t":0,"_vc":0},{"_i":"ms_005100.jpg","_t":5100,"_vc":11},{"_i":"ms_005300.jpg","_t":5300,"_vc":11},{"_i":"ms_005700.jpg","_t":5700,"_vc":11},{"_i":"ms_006100.jpg","_t":6100,"_vc":11},{"_i":"ms_006200.jpg","_t":6200,"_vc":11},{"_i":"ms_006600.jpg","_t":6600,"_vc":11},{"_i":"ms_006800.jpg","_t":6800,"_vc":11},{"_i":"ms_006900.jpg","_t":6900,"_vc":11},{"_i":"ms_007100.jpg","_t":7100,"_vc":24},{"_i":"ms_007400.jpg","_t":7400,"_vc":32},{"_i":"ms_009700.jpg","_t":9700,"_vc":32},{"_i":"ms_010000.jpg","_t":10000,"_vc":32},{"_i":"ms_010500.jpg","_t":10500,"_vc":32},{"_i":"ms_010800.jpg","_t":10800,"_vc":32},{"_i":"ms_011000.jpg","_t":11000,"_vc":32},{"_i":"ms_011100.jpg","_t":11100,"_vc":34},{"_i":"ms_011200.jpg","_t":11200,"_vc":35},{"_i":"ms_011300.jpg","_t":11300,"_vc":35},{"_i":"ms_011400.jpg","_t":11400,"_vc":36},{"_i":"ms_011500.jpg","_t":11500,"_vc":36},{"_i":"ms_011600.jpg","_t":11600,"_vc":36},{"_i":"ms_012000.jpg","_t":12000,"_vc":36},{"_i":"ms_012300.jpg","_t":12300,"_vc":36},{"_i":"ms_012500.jpg","_t":12500,"_vc":36},{"_i":"ms_012800.jpg","_t":12800,"_vc":36},{"_i":"ms_013000.jpg","_t":13000,"_vc":36},{"_i":"ms_013600.jpg","_t":13600,"_vc":36},{"_i":"ms_013700.jpg","_t":13700,"_vc":36},{"_i":"ms_013800.jpg","_t":13800,"_vc":36},{"_i":"ms_015500.jpg","_t":15500,"_vc":36},{"_i":"ms_015900.jpg","_t":15900,"_vc":36},{"_i":"ms_016300.jpg","_t":16300,"_vc":68},{"_i":"ms_016500.jpg","_t":16500,"_vc":69},{"_i":"ms_016600.jpg","_t":16600,"_vc":71},{"_i":"ms_016700.jpg","_t":16700,"_vc":70},{"_i":"ms_017000.jpg","_t":17000,"_vc":70},{"_i":"ms_017100.jpg","_t":17100,"_vc":70},{"_i":"ms_017200.jpg","_t":17200,"_vc":99},{"_i":"ms_017300.jpg","_t":17300,"_vc":99},{"_i":"ms_017400.jpg","_t":17400,"_vc":100},{"_i":"ms_017500.jpg","_t":17500,"_vc":100}]],"visualComplete":[17400],"lighthouse":[35],"pagespeed":[63]}}