{"_ts":[1546329829,1546373928],"_r":{"breakdown":{"html":{"bytes":[9518,9519],"requests":[2,2]},"js":{"bytes":[304738,304734],"requests":[8,8]},"css":{"bytes":[81363,81293],"requests":[6,6]},"image":{"bytes":[203650,203419],"requests":[20,20]},"flash":{"bytes":[0,0],"requests":[0,0]},"font":{"bytes":[536924,536924],"requests":[6,6]},"video":{"bytes":[0,0],"requests":[0,0]},"other":{"bytes":[3285,3266],"requests":[6,6]}},"date":[1546329829,1546373928],"domElements":[589,589],"domInteractive":[3569,3303],"firstPaint":[2341.5000000005,2389.4],"fullyLoaded":[5444,5319],"id":["190101_V8_4d393153019dea5c1c373f2cd73ce0ab","190101_4F_c2484cafdf282c06798b33bd89da1851"],"loadTime":[5228,5095],"render":[2400,2400],"SpeedIndex":[3497,3225],"TTFB":[1353,1440],"videoFrames":[[{"_i":"ms_000000.jpg","_t":0,"_vc":0},{"_i":"ms_002400.jpg","_t":2400,"_vc":6},{"_i":"ms_002600.jpg","_t":2600,"_vc":7},{"_i":"ms_002700.jpg","_t":2700,"_vc":6},{"_i":"ms_002800.jpg","_t":2800,"_vc":6},{"_i":"ms_003300.jpg","_t":3300,"_vc":7},{"_i":"ms_003500.jpg","_t":3500,"_vc":89},{"_i":"ms_003800.jpg","_t":3800,"_vc":90},{"_i":"ms_004000.jpg","_t":4000,"_vc":94},{"_i":"ms_004200.jpg","_t":4200,"_vc":99},{"_i":"ms_004300.jpg","_t":4300,"_vc":100}],[{"_i":"ms_000000.jpg","_t":0,"_vc":0},{"_i":"ms_002400.jpg","_t":2400,"_vc":6},{"_i":"ms_002600.jpg","_t":2600,"_vc":6},{"_i":"ms_002700.jpg","_t":2700,"_vc":6},{"_i":"ms_002800.jpg","_t":2800,"_vc":6},{"_i":"ms_003200.jpg","_t":3200,"_vc":89},{"_i":"ms_003300.jpg","_t":3300,"_vc":89},{"_i":"ms_003500.jpg","_t":3500,"_vc":90},{"_i":"ms_003700.jpg","_t":3700,"_vc":93},{"_i":"ms_003800.jpg","_t":3800,"_vc":94},{"_i":"ms_003900.jpg","_t":3900,"_vc":94},{"_i":"ms_004000.jpg","_t":4000,"_vc":99},{"_i":"ms_004100.jpg","_t":4100,"_vc":100}]],"visualComplete":[4300,4100],"lighthouse":[31,31],"pagespeed":[72,73]}}