{"_ts":[1549010282,1549075146,1549097667,1549141772],"_r":{"breakdown":{"html":{"bytes":[30062,29112,29845,29758],"requests":[28,26,29,30]},"js":{"bytes":[638233,562655,589747,639900],"requests":[33,31,31,33]},"css":{"bytes":[259035,281216,281216,281216],"requests":[6,7,7,7]},"image":{"bytes":[571709,571286,571286,571710],"requests":[36,24,24,35]},"flash":{"bytes":[0,0,0,0],"requests":[0,0,0,0]},"font":{"bytes":[0,0,0,0],"requests":[0,0,0,0]},"video":{"bytes":[5004490,5004490,5004490,5004490],"requests":[1,1,1,1]},"other":{"bytes":[246,242,242,242],"requests":[35,7,8,32]}},"date":[1549010282,1549075146,1549097667,1549141772],"domElements":[970,953,953,970],"domInteractive":[3640,2672,3113,2917],"firstPaint":[3177.6649999956,2231.7749999929,2742.9600000032,2458.9799999994],"fullyLoaded":[18015,14444,14799,16406],"id":["190201_ND_f381990e78f2d60e22bce05434eb2ba1","190202_K8_d8660d963dfa45b3cf6b0b15452aab62","190202_YH_146a155342f790513b259e5c73dcbbb1","190202_GG_d87659d02e69e8517c348464e1f77de0"],"loadTime":[15632,11251,11171,14242],"render":[3300,2200,2700,2500],"SpeedIndex":[5983,4750,5210,5164],"TTFB":[1954,1392,2051,1694],"videoFrames":[[{"_i":"ms_000000.jpg","_t":0,"_vc":0},{"_i":"ms_003300.jpg","_t":3300,"_vc":46},{"_i":"ms_003400.jpg","_t":3400,"_vc":46},{"_i":"ms_003900.jpg","_t":3900,"_vc":47},{"_i":"ms_004000.jpg","_t":4000,"_vc":48},{"_i":"ms_004100.jpg","_t":4100,"_vc":48},{"_i":"ms_004200.jpg","_t":4200,"_vc":48},{"_i":"ms_004400.jpg","_t":4400,"_vc":48},{"_i":"ms_004900.jpg","_t":4900,"_vc":50},{"_i":"ms_005000.jpg","_t":5000,"_vc":50},{"_i":"ms_005100.jpg","_t":5100,"_vc":48},{"_i":"ms_005600.jpg","_t":5600,"_vc":48},{"_i":"ms_006200.jpg","_t":6200,"_vc":50},{"_i":"ms_006300.jpg","_t":6300,"_vc":53},{"_i":"ms_006400.jpg","_t":6400,"_vc":51},{"_i":"ms_006900.jpg","_t":6900,"_vc":39},{"_i":"ms_007000.jpg","_t":7000,"_vc":52},{"_i":"ms_007100.jpg","_t":7100,"_vc":56},{"_i":"ms_007200.jpg","_t":7200,"_vc":55},{"_i":"ms_007300.jpg","_t":7300,"_vc":55},{"_i":"ms_007400.jpg","_t":7400,"_vc":54},{"_i":"ms_007500.jpg","_t":7500,"_vc":54},{"_i":"ms_007600.jpg","_t":7600,"_vc":54},{"_i":"ms_007700.jpg","_t":7700,"_vc":54},{"_i":"ms_007800.jpg","_t":7800,"_vc":54},{"_i":"ms_007900.jpg","_t":7900,"_vc":95},{"_i":"ms_008000.jpg","_t":8000,"_vc":96},{"_i":"ms_008100.jpg","_t":8100,"_vc":96},{"_i":"ms_008200.jpg","_t":8200,"_vc":96},{"_i":"ms_008300.jpg","_t":8300,"_vc":96},{"_i":"ms_008500.jpg","_t":8500,"_vc":96},{"_i":"ms_009000.jpg","_t":9000,"_vc":98},{"_i":"ms_009500.jpg","_t":9500,"_vc":98},{"_i":"ms_010000.jpg","_t":10000,"_vc":97},{"_i":"ms_010500.jpg","_t":10500,"_vc":98},{"_i":"ms_011000.jpg","_t":11000,"_vc":99},{"_i":"ms_011500.jpg","_t":11500,"_vc":97},{"_i":"ms_012000.jpg","_t":12000,"_vc":97},{"_i":"ms_012500.jpg","_t":12500,"_vc":97},{"_i":"ms_013000.jpg","_t":13000,"_vc":97},{"_i":"ms_014000.jpg","_t":14000,"_vc":97},{"_i":"ms_015000.jpg","_t":15000,"_vc":95},{"_i":"ms_016000.jpg","_t":16000,"_vc":95},{"_i":"ms_017000.jpg","_t":17000,"_vc":97},{"_i":"ms_018000.jpg","_t":18000,"_vc":98},{"_i":"ms_019000.jpg","_t":19000,"_vc":99},{"_i":"ms_019100.jpg","_t":19100,"_vc":100}],[{"_i":"ms_000000.jpg","_t":0,"_vc":0},{"_i":"ms_002200.jpg","_t":2200,"_vc":30},{"_i":"ms_002300.jpg","_t":2300,"_vc":46},{"_i":"ms_002400.jpg","_t":2400,"_vc":46},{"_i":"ms_002800.jpg","_t":2800,"_vc":48},{"_i":"ms_002900.jpg","_t":2900,"_vc":48},{"_i":"ms_003000.jpg","_t":3000,"_vc":45},{"_i":"ms_003100.jpg","_t":3100,"_vc":48},{"_i":"ms_003400.jpg","_t":3400,"_vc":48},{"_i":"ms_004000.jpg","_t":4000,"_vc":49},{"_i":"ms_004500.jpg","_t":4500,"_vc":49},{"_i":"ms_004800.jpg","_t":4800,"_vc":49},{"_i":"ms_005000.jpg","_t":5000,"_vc":49},{"_i":"ms_005300.jpg","_t":5300,"_vc":52},{"_i":"ms_005400.jpg","_t":5400,"_vc":52},{"_i":"ms_005600.jpg","_t":5600,"_vc":53},{"_i":"ms_005700.jpg","_t":5700,"_vc":51},{"_i":"ms_006200.jpg","_t":6200,"_vc":48},{"_i":"ms_006400.jpg","_t":6400,"_vc":39},{"_i":"ms_006500.jpg","_t":6500,"_vc":50},{"_i":"ms_006600.jpg","_t":6600,"_vc":55},{"_i":"ms_006700.jpg","_t":6700,"_vc":55},{"_i":"ms_006800.jpg","_t":6800,"_vc":96},{"_i":"ms_006900.jpg","_t":6900,"_vc":96},{"_i":"ms_007000.jpg","_t":7000,"_vc":96},{"_i":"ms_007100.jpg","_t":7100,"_vc":97},{"_i":"ms_007200.jpg","_t":7200,"_vc":97},{"_i":"ms_007500.jpg","_t":7500,"_vc":97},{"_i":"ms_008000.jpg","_t":8000,"_vc":98},{"_i":"ms_008500.jpg","_t":8500,"_vc":99},{"_i":"ms_009000.jpg","_t":9000,"_vc":99},{"_i":"ms_009500.jpg","_t":9500,"_vc":99},{"_i":"ms_010000.jpg","_t":10000,"_vc":99},{"_i":"ms_010500.jpg","_t":10500,"_vc":99},{"_i":"ms_011000.jpg","_t":11000,"_vc":98},{"_i":"ms_011500.jpg","_t":11500,"_vc":97},{"_i":"ms_012000.jpg","_t":12000,"_vc":99},{"_i":"ms_012500.jpg","_t":12500,"_vc":99},{"_i":"ms_013000.jpg","_t":13000,"_vc":98},{"_i":"ms_013500.jpg","_t":13500,"_vc":98},{"_i":"ms_014000.jpg","_t":14000,"_vc":100},{"_i":"ms_014500.jpg","_t":14500,"_vc":97},{"_i":"ms_015000.jpg","_t":15000,"_vc":97},{"_i":"ms_015500.jpg","_t":15500,"_vc":98},{"_i":"ms_016000.jpg","_t":16000,"_vc":98},{"_i":"ms_016500.jpg","_t":16500,"_vc":100}],[{"_i":"ms_000000.jpg","_t":0,"_vc":0},{"_i":"ms_002700.jpg","_t":2700,"_vc":45},{"_i":"ms_002800.jpg","_t":2800,"_vc":45},{"_i":"ms_003000.jpg","_t":3000,"_vc":46},{"_i":"ms_003200.jpg","_t":3200,"_vc":46},{"_i":"ms_003300.jpg","_t":3300,"_vc":47},{"_i":"ms_003400.jpg","_t":3400,"_vc":48},{"_i":"ms_003800.jpg","_t":3800,"_vc":50},{"_i":"ms_003900.jpg","_t":3900,"_vc":48},{"_i":"ms_005700.jpg","_t":5700,"_vc":50},{"_i":"ms_005800.jpg","_t":5800,"_vc":50},{"_i":"ms_006100.jpg","_t":6100,"_vc":39},{"_i":"ms_006200.jpg","_t":6200,"_vc":55},{"_i":"ms_006300.jpg","_t":6300,"_vc":58},{"_i":"ms_006400.jpg","_t":6400,"_vc":58},{"_i":"ms_006500.jpg","_t":6500,"_vc":55},{"_i":"ms_006600.jpg","_t":6600,"_vc":55},{"_i":"ms_006700.jpg","_t":6700,"_vc":55},{"_i":"ms_006800.jpg","_t":6800,"_vc":55},{"_i":"ms_006900.jpg","_t":6900,"_vc":55},{"_i":"ms_007000.jpg","_t":7000,"_vc":55},{"_i":"ms_007100.jpg","_t":7100,"_vc":55},{"_i":"ms_007200.jpg","_t":7200,"_vc":96},{"_i":"ms_007300.jpg","_t":7300,"_vc":96},{"_i":"ms_007400.jpg","_t":7400,"_vc":96},{"_i":"ms_007500.jpg","_t":7500,"_vc":96},{"_i":"ms_007600.jpg","_t":7600,"_vc":96},{"_i":"ms_007700.jpg","_t":7700,"_vc":97},{"_i":"ms_008000.jpg","_t":8000,"_vc":97},{"_i":"ms_008500.jpg","_t":8500,"_vc":99},{"_i":"ms_009000.jpg","_t":9000,"_vc":97},{"_i":"ms_009500.jpg","_t":9500,"_vc":99},{"_i":"ms_010000.jpg","_t":10000,"_vc":99},{"_i":"ms_010500.jpg","_t":10500,"_vc":99},{"_i":"ms_011000.jpg","_t":11000,"_vc":97},{"_i":"ms_011500.jpg","_t":11500,"_vc":97},{"_i":"ms_012000.jpg","_t":12000,"_vc":99},{"_i":"ms_012500.jpg","_t":12500,"_vc":98},{"_i":"ms_013000.jpg","_t":13000,"_vc":98},{"_i":"ms_013500.jpg","_t":13500,"_vc":99},{"_i":"ms_014000.jpg","_t":14000,"_vc":96},{"_i":"ms_014500.jpg","_t":14500,"_vc":96},{"_i":"ms_015000.jpg","_t":15000,"_vc":96},{"_i":"ms_015500.jpg","_t":15500,"_vc":97},{"_i":"ms_016000.jpg","_t":16000,"_vc":97},{"_i":"ms_016500.jpg","_t":16500,"_vc":99},{"_i":"ms_016700.jpg","_t":16700,"_vc":100}],[{"_i":"ms_000000.jpg","_t":0,"_vc":0},{"_i":"ms_002500.jpg","_t":2500,"_vc":46},{"_i":"ms_002600.jpg","_t":2600,"_vc":46},{"_i":"ms_002700.jpg","_t":2700,"_vc":46},{"_i":"ms_002800.jpg","_t":2800,"_vc":46},{"_i":"ms_003200.jpg","_t":3200,"_vc":48},{"_i":"ms_003400.jpg","_t":3400,"_vc":50},{"_i":"ms_003500.jpg","_t":3500,"_vc":50},{"_i":"ms_003600.jpg","_t":3600,"_vc":48},{"_i":"ms_005100.jpg","_t":5100,"_vc":49},{"_i":"ms_005400.jpg","_t":5400,"_vc":51},{"_i":"ms_005500.jpg","_t":5500,"_vc":51},{"_i":"ms_005600.jpg","_t":5600,"_vc":51},{"_i":"ms_005700.jpg","_t":5700,"_vc":53},{"_i":"ms_005800.jpg","_t":5800,"_vc":50},{"_i":"ms_006300.jpg","_t":6300,"_vc":47},{"_i":"ms_006900.jpg","_t":6900,"_vc":68},{"_i":"ms_007000.jpg","_t":7000,"_vc":95},{"_i":"ms_007300.jpg","_t":7300,"_vc":95},{"_i":"ms_007400.jpg","_t":7400,"_vc":95},{"_i":"ms_007500.jpg","_t":7500,"_vc":96},{"_i":"ms_008000.jpg","_t":8000,"_vc":96},{"_i":"ms_008500.jpg","_t":8500,"_vc":96},{"_i":"ms_009000.jpg","_t":9000,"_vc":98},{"_i":"ms_009500.jpg","_t":9500,"_vc":98},{"_i":"ms_010000.jpg","_t":10000,"_vc":99},{"_i":"ms_010500.jpg","_t":10500,"_vc":99},{"_i":"ms_011000.jpg","_t":11000,"_vc":99},{"_i":"ms_011500.jpg","_t":11500,"_vc":97},{"_i":"ms_012000.jpg","_t":12000,"_vc":97},{"_i":"ms_012500.jpg","_t":12500,"_vc":97},{"_i":"ms_013000.jpg","_t":13000,"_vc":97},{"_i":"ms_013500.jpg","_t":13500,"_vc":97},{"_i":"ms_014000.jpg","_t":14000,"_vc":97},{"_i":"ms_014500.jpg","_t":14500,"_vc":97},{"_i":"ms_015000.jpg","_t":15000,"_vc":91},{"_i":"ms_015500.jpg","_t":15500,"_vc":95},{"_i":"ms_016000.jpg","_t":16000,"_vc":95},{"_i":"ms_016500.jpg","_t":16500,"_vc":96},{"_i":"ms_017000.jpg","_t":17000,"_vc":98},{"_i":"ms_017500.jpg","_t":17500,"_vc":99},{"_i":"ms_018000.jpg","_t":18000,"_vc":100},{"_i":"ms_018400.jpg","_t":18400,"_vc":100}]],"visualComplete":[19100,14000,16700,18000],"lighthouse":[42,42,42,42],"pagespeed":[84,84,83,84],"TTFI":[null,2737,3169,2956]}}